LICENSE
MANIFEST.in
README.md
setup.py
z80.h
z80/__init__.py
z80/_disasm.py
z80/_disasm_parser.py
z80/_error.py
z80/_instr.py
z80/_machine.py
z80/_main.py
z80/_source.py
z80/_token.py
z80/_z80module.cpp
z80/machine.inc
z80.egg-info/PKG-INFO
z80.egg-info/SOURCES.txt
z80.egg-info/dependency_links.txt
z80.egg-info/entry_points.txt
z80.egg-info/top_level.txt