Metadata-Version: 2.1
Name: z80
Version: 1.0b3
Summary: Fast and flexible Z80/i8080 Emulator
Home-page: https://github.com/kosarev/z80
Author: Ivan Kosarev
Author-email: mail@ivankosarev.com
License: MIT
Platform: UNKNOWN
Classifier: Development Status :: 4 - Beta
Classifier: Intended Audience :: Developers
Classifier: Intended Audience :: Information Technology
Classifier: Intended Audience :: Education
Classifier: License :: OSI Approved :: MIT License
Classifier: Operating System :: OS Independent
Classifier: Programming Language :: C++
Classifier: Programming Language :: Python :: 3
Classifier: Programming Language :: Python :: Implementation :: CPython
Classifier: Topic :: Software Development
Classifier: Topic :: Software Development :: Libraries
Classifier: Topic :: System :: Emulators
License-File: LICENSE
